Workbook

Sheet Monthly Budget
A1: Monthly Budget Planner
A2: Blue cells are inputs. Actual column (green) = 90-day monthly average from your card data (Spending Summary sheet).
A4: INCOME
A5: Source | B5: Monthly Amount ($)
A6: Salary (take-home) | B6: 5000
A7: Other Income | B7: 200
A8: Total Income | B8: =SUM(B6:B7)
A10: EXPENSES
A11: Category | B11: Budgeted ($) | C11: Actual ($) | D11: Difference ($) | E11: % of Income
A12: Rent / Mortgage | B12: 1800 | C12: 0 | D12: =B12-C12 | E12: =IF($B$8=0,0,B12/$B$8)
A13: Utilities | B13: 150 | C13: 0 | D13: =B13-C13 | E13: =IF($B$8=0,0,B13/$B$8)
A14: Internet & Phone | B14: 90 | C14: ='Spending Summary'!G9 | D14: =B14-C14 | E14: =IF($B$8=0,0,B14/$B$8)
A15: Insurance | B15: 200 | C15: 0 | D15: =B15-C15 | E15: =IF($B$8=0,0,B15/$B$8)
A16: Car Payment | B16: 350 | C16: 0 | D16: =B16-C16 | E16: =IF($B$8=0,0,B16/$B$8)
A17: Debt Payments | B17: 250 | C17: 0 | D17: =B17-C17 | E17: =IF($B$8=0,0,B17/$B$8)
A18: Groceries | B18: 500 | C18: ='Spending Summary'!G8 | D18: =B18-C18 | E18: =IF($B$8=0,0,B18/$B$8)
A19: Gas / Transit | B19: 150 | C19: ='Spending Summary'!G11 | D19: =B19-C19 | E19: =IF($B$8=0,0,B19/$B$8)
A20: Dining Out | B20: 250 | C20: ='Spending Summary'!G7 | D20: =B20-C20 | E20: =IF($B$8=0,0,B20/$B$8)
A21: Entertainment | B21: 100 | C21: ='Spending Summary'!G12 | D21: =B21-C21 | E21: =IF($B$8=0,0,B21/$B$8)
A22: Subscriptions | B22: 60 | C22: ='Spending Summary'!G14 | D22: =B22-C22 | E22: =IF($B$8=0,0,B22/$B$8)
A23: Health & Fitness | B23: 80 | C23: ='Spending Summary'!G10 | D23: =B23-C23 | E23: =IF($B$8=0,0,B23/$B$8)
A24: Personal Care | B24: 75 | C24: ='Spending Summary'!G15 | D24: =B24-C24 | E24: =IF($B$8=0,0,B24/$B$8)
A25: Shopping | B25: 150 | C25: ='Spending Summary'!G6 | D25: =B25-C25 | E25: =IF($B$8=0,0,B25/$B$8)
A26: Miscellaneous | B26: 100 | C26: ='Spending Summary'!G13 | D26: =B26-C26 | E26: =IF($B$8=0,0,B26/$B$8)
A27: Total Expenses | B27: =SUM(B12:B26) | C27: =SUM(C12:C26) | D27: =B27-C27 | E27: =IF($B$8=0,0,B27/$B$8)
A29: SUMMARY
B30: Budgeted ($) | C30: Actual ($)
A31: Total Income | B31: =$B$8 | C31: =$B$8
A32: Total Expenses | B32: =B27 | C32: =C27
A33: Savings | B33: =B31-B32 | C33: =C31-C32
A34: Savings Rate | B34: =IF(B31=0,0,B33/B31) | C34: =IF(C31=0,0,C33/C31)

Sheet Annual Tracker
A1: Annual Expense Tracker
A2: Enter actuals each month (blue cells)
A4: Category | B4: Jan | C4: Feb | D4: Mar | E4: Apr | F4: May | G4: Jun | H4: Jul | I4: Aug | J4: Sep | K4: Oct | L4: Nov | M4: Dec | N4: Total ($) | O4: Monthly Avg ($)
A5: Income | B5: 0 | C5: 0 | D5: 0 | E5: 0 | F5: 0 | G5: 0 | H5: 0 | I5: 0 | J5: 0 | K5: 0 | L5: 0 | M5: 0 | N5: =SUM(B5:M5) | O5: =AVERAGE(B5:M5)
A6: Rent / Mortgage | B6: 0 | C6: 0 | D6: 0 | E6: 0 | F6: 0 | G6: 0 | H6: 0 | I6: 0 | J6: 0 | K6: 0 | L6: 0 | M6: 0 | N6: =SUM(B6:M6) | O6: =AVERAGE(B6:M6)
A7: Utilities | B7: 0 | C7: 0 | D7: 0 | E7: 0 | F7: 0 | G7: 0 | H7: 0 | I7: 0 | J7: 0 | K7: 0 | L7: 0 | M7: 0 | N7: =SUM(B7:M7) | O7: =AVERAGE(B7:M7)
A8: Internet & Phone | B8: 0 | C8: 0 | D8: 0 | E8: 0 | F8: 0 | G8: 0 | H8: 0 | I8: 0 | J8: 0 | K8: 0 | L8: 0 | M8: 0 | N8: =SUM(B8:M8) | O8: =AVERAGE(B8:M8)
A9: Insurance | B9: 0 | C9: 0 | D9: 0 | E9: 0 | F9: 0 | G9: 0 | H9: 0 | I9: 0 | J9: 0 | K9: 0 | L9: 0 | M9: 0 | N9: =SUM(B9:M9) | O9: =AVERAGE(B9:M9)
A10: Car Payment | B10: 0 | C10: 0 | D10: 0 | E10: 0 | F10: 0 | G10: 0 | H10: 0 | I10: 0 | J10: 0 | K10: 0 | L10: 0 | M10: 0 | N10: =SUM(B10:M10) | O10: =AVERAGE(B10:M10)
A11: Debt Payments | B11: 0 | C11: 0 | D11: 0 | E11: 0 | F11: 0 | G11: 0 | H11: 0 | I11: 0 | J11: 0 | K11: 0 | L11: 0 | M11: 0 | N11: =SUM(B11:M11) | O11: =AVERAGE(B11:M11)
A12: Groceries | B12: 0 | C12: 0 | D12: 0 | E12: 0 | F12: 0 | G12: 0 | H12: 0 | I12: 0 | J12: 0 | K12: 0 | L12: 0 | M12: 0 | N12: =SUM(B12:M12) | O12: =AVERAGE(B12:M12)
A13: Gas / Transit | B13: 0 | C13: 0 | D13: 0 | E13: 0 | F13: 0 | G13: 0 | H13: 0 | I13: 0 | J13: 0 | K13: 0 | L13: 0 | M13: 0 | N13: =SUM(B13:M13) | O13: =AVERAGE(B13:M13)
A14: Dining Out | B14: 0 | C14: 0 | D14: 0 | E14: 0 | F14: 0 | G14: 0 | H14: 0 | I14: 0 | J14: 0 | K14: 0 | L14: 0 | M14: 0 | N14: =SUM(B14:M14) | O14: =AVERAGE(B14:M14)
A15: Entertainment | B15: 0 | C15: 0 | D15: 0 | E15: 0 | F15: 0 | G15: 0 | H15: 0 | I15: 0 | J15: 0 | K15: 0 | L15: 0 | M15: 0 | N15: =SUM(B15:M15) | O15: =AVERAGE(B15:M15)
A16: Subscriptions | B16: 0 | C16: 0 | D16: 0 | E16: 0 | F16: 0 | G16: 0 | H16: 0 | I16: 0 | J16: 0 | K16: 0 | L16: 0 | M16: 0 | N16: =SUM(B16:M16) | O16: =AVERAGE(B16:M16)
... A20: Miscellaneous | B20: 0 | C20: 0 | D20: 0 | E20: 0 | F20: 0 | G20: 0 | H20: 0 | I20: 0 | J20: 0 | K20: 0 | L20: 0 | M20: 0 | N20: =SUM(B20:M20) | O20: =AVERAGE(B20:M20)
A21: Total Expenses | B21: =SUM(B6:B20) | C21: =SUM(C6:C20) | D21: =SUM(D6:D20) | E21: =SUM(E6:E20) | F21: =SUM(F6:F20) | G21: =SUM(G6:G20) | H21: =SUM(H6:H20) | I21: =SUM(I6:I20) | ... M21: =SUM(M6:M20) | N21: =SUM(B21:M21) | O21: =AVERAGE(B21:M21)
A22: Savings | B22: =B5-B21 | C22: =C5-C21 | D22: =D5-D21 | E22: =E5-E21 | F22: =F5-F21 | G22: =G5-G21 | H22: =H5-H21 | I22: =I5-I21 | ... M22: =M5-M21 | N22: =SUM(B22:M22) | O22: =AVERAGE(B22:M22)
A23: Savings Rate | B23: =IF(B5=0,0,B22/B5) | C23: =IF(C5=0,0,C22/C5) | D23: =IF(D5=0,0,D22/D5) | E23: =IF(E5=0,0,E22/E5) | F23: =IF(F5=0,0,F22/F5) | G23: =IF(G5=0,0,G22/G5) | H23: =IF(H5=0,0,H22/H5) | I23: =IF(I5=0,0,I22/I5) | ... N23: =IF(N5=0,0,N22/N5) | O23: =N23

Sheet Transactions
A1: Date | B1: Description | C1: Amount ($) | D1: Category | E1: Month
A2: 46093 | B2: AplPay BRIDGELAND: ACypress TX | C2: 25 | D2: Miscellaneous | E2: Mar 2026
A3: 46093 | B3: AplPay FIRST WATCH #CYPRESS TX | C3: 42.39 | D3: Dining Out | E3: Mar 2026
A4: 46093 | B4: DIL SE INDIAN FOOD TCypress TX | C4: 12.98 | D4: Dining Out | E4: Mar 2026
A5: 46094 | B5: AMAZON MARKEPLACE NA PA | C5: 30.56 | D5: Shopping | E5: Mar 2026
A6: 46094 | B6: AMERICAN EAGLE OUTFIPITTSBURGH PA | C6: 117.3 | D6: Shopping | E6: Mar 2026
A7: 46094 | B7: EXXONMOBIL CYPRESS TX | C7: 43.91 | D7: Gas / Transit | E7: Mar 2026
A8: 46094 | B8: MOBILE PAYMENT - THANK YOU | C8: -2062.28 | D8: Payments & Adjustments | E8: Mar 2026
A9: 46094 | B9: PACSUN #0680 0680 HOUSTON TX | C9: 127.19 | D9: Shopping | E9: Mar 2026
A10: 46094 | B10: STARBUCKS STORE 7147CYPRESS TX | C10: 9.96 | D10: Dining Out | E10: Mar 2026
A11: 46094 | B11: TST* NAGAS SOUTH INDHOUSTON TX | C11: 51.93 | D11: Dining Out | E11: Mar 2026
A12: 46094 | B12: ZARA USA 1223 1223 HOUSTON TX | C12: 129.57 | D12: Shopping | E12: Mar 2026
A13: 46095 | B13: AMAZON MARKEPLACE NA PA | C13: 8.09 | D13: Shopping | E13: Mar 2026
... A403: 46182 | B403: MOBILE PAYMENT - THANK YOU | C403: -1567.13 | D403: Payments & Adjustments | E403: Jun 2026

Sheet Spending Summary
A1: 90-Day Spending Summary (Mar 12 – Jun 9, 2026)
A2: Card charges net of refunds. Card payments excluded. Travel is one-off trip spend — tracked separately from monthly categories.
A4: Category | B4: Mar 2026 ($) | C4: Apr 2026 ($) | D4: May 2026 ($) | E4: Jun 2026 ($) | F4: Total ($) | G4: Monthly Avg ($) | H4: % of Spend
A5: Travel | B5: =SUMIFS(Transactions!$C$2:$C$403,Transactions!$D$2:$D$403,$A5,Transactions!$E$2:$E$403,"Mar 2026") | C5: =SUMIFS(Transactions!$C$2:$C$403,Transactions!$D$2:$D$403,$A5,Transactions!$E$2:$E$403,"Apr 2026") | D5: =SUMIFS(Transactions!$C$2:$C$403,Transactions!$D$2:$D$403,$A5,Transactions!$E$2:$E$403,"May 2026") | E5: =SUMIFS(Transactions!$C$2:$C$403,Transactions!$D$2:$D$403,$A5,Transactions!$E$2:$E$403,"Jun 2026") | F5: =SUM(B5:E5) | G5: =F5/3 | H5: =IF($F$16=0,0,F5/$F$16)
A6: Shopping | B6: =SUMIFS(Transactions!$C$2:$C$403,Transactions!$D$2:$D$403,$A6,Transactions!$E$2:$E$403,"Mar 2026") | C6: =SUMIFS(Transactions!$C$2:$C$403,Transactions!$D$2:$D$403,$A6,Transactions!$E$2:$E$403,"Apr 2026") | D6: =SUMIFS(Transactions!$C$2:$C$403,Transactions!$D$2:$D$403,$A6,Transactions!$E$2:$E$403,"May 2026") | E6: =SUMIFS(Transactions!$C$2:$C$403,Transactions!$D$2:$D$403,$A6,Transactions!$E$2:$E$403,"Jun 2026") | F6: =SUM(B6:E6) | G6: =F6/3 | H6: =IF($F$16=0,0,F6/$F$16)
A7: Dining Out | B7: =SUMIFS(Transactions!$C$2:$C$403,Transactions!$D$2:$D$403,$A7,Transactions!$E$2:$E$403,"Mar 2026") | C7: =SUMIFS(Transactions!$C$2:$C$403,Transactions!$D$2:$D$403,$A7,Transactions!$E$2:$E$403,"Apr 2026") | D7: =SUMIFS(Transactions!$C$2:$C$403,Transactions!$D$2:$D$403,$A7,Transactions!$E$2:$E$403,"May 2026") | E7: =SUMIFS(Transactions!$C$2:$C$403,Transactions!$D$2:$D$403,$A7,Transactions!$E$2:$E$403,"Jun 2026") | F7: =SUM(B7:E7) | G7: =F7/3 | H7: =IF($F$16=0,0,F7/$F$16)
A8: Groceries | B8: =SUMIFS(Transactions!$C$2:$C$403,Transactions!$D$2:$D$403,$A8,Transactions!$E$2:$E$403,"Mar 2026") | C8: =SUMIFS(Transactions!$C$2:$C$403,Transactions!$D$2:$D$403,$A8,Transactions!$E$2:$E$403,"Apr 2026") | D8: =SUMIFS(Transactions!$C$2:$C$403,Transactions!$D$2:$D$403,$A8,Transactions!$E$2:$E$403,"May 2026") | E8: =SUMIFS(Transactions!$C$2:$C$403,Transactions!$D$2:$D$403,$A8,Transactions!$E$2:$E$403,"Jun 2026") | F8: =SUM(B8:E8) | G8: =F8/3 | H8: =IF($F$16=0,0,F8/$F$16)
A9: Internet & Phone | B9: =SUMIFS(Transactions!$C$2:$C$403,Transactions!$D$2:$D$403,$A9,Transactions!$E$2:$E$403,"Mar 2026") | C9: =SUMIFS(Transactions!$C$2:$C$403,Transactions!$D$2:$D$403,$A9,Transactions!$E$2:$E$403,"Apr 2026") | D9: =SUMIFS(Transactions!$C$2:$C$403,Transactions!$D$2:$D$403,$A9,Transactions!$E$2:$E$403,"May 2026") | E9: =SUMIFS(Transactions!$C$2:$C$403,Transactions!$D$2:$D$403,$A9,Transactions!$E$2:$E$403,"Jun 2026") | F9: =SUM(B9:E9) | G9: =F9/3 | H9: =IF($F$16=0,0,F9/$F$16)
A10: Health & Fitness | B10: =SUMIFS(Transactions!$C$2:$C$403,Transactions!$D$2:$D$403,$A10,Transactions!$E$2:$E$403,"Mar 2026") | C10: =SUMIFS(Transactions!$C$2:$C$403,Transactions!$D$2:$D$403,$A10,Transactions!$E$2:$E$403,"Apr 2026") | D10: =SUMIFS(Transactions!$C$2:$C$403,Transactions!$D$2:$D$403,$A10,Transactions!$E$2:$E$403,"May 2026") | E10: =SUMIFS(Transactions!$C$2:$C$403,Transactions!$D$2:$D$403,$A10,Transactions!$E$2:$E$403,"Jun 2026") | F10: =SUM(B10:E10) | G10: =F10/3 | H10: =IF($F$16=0,0,F10/$F$16)
A11: Gas / Transit | B11: =SUMIFS(Transactions!$C$2:$C$403,Transactions!$D$2:$D$403,$A11,Transactions!$E$2:$E$403,"Mar 2026") | C11: =SUMIFS(Transactions!$C$2:$C$403,Transactions!$D$2:$D$403,$A11,Transactions!$E$2:$E$403,"Apr 2026") | D11: =SUMIFS(Transactions!$C$2:$C$403,Transactions!$D$2:$D$403,$A11,Transactions!$E$2:$E$403,"May 2026") | E11: =SUMIFS(Transactions!$C$2:$C$403,Transactions!$D$2:$D$403,$A11,Transactions!$E$2:$E$403,"Jun 2026") | F11: =SUM(B11:E11) | G11: =F11/3 | H11: =IF($F$16=0,0,F11/$F$16)
A12: Entertainment | B12: =SUMIFS(Transactions!$C$2:$C$403,Transactions!$D$2:$D$403,$A12,Transactions!$E$2:$E$403,"Mar 2026") | C12: =SUMIFS(Transactions!$C$2:$C$403,Transactions!$D$2:$D$403,$A12,Transactions!$E$2:$E$403,"Apr 2026") | D12: =SUMIFS(Transactions!$C$2:$C$403,Transactions!$D$2:$D$403,$A12,Transactions!$E$2:$E$403,"May 2026") | E12: =SUMIFS(Transactions!$C$2:$C$403,Transactions!$D$2:$D$403,$A12,Transactions!$E$2:$E$403,"Jun 2026") | F12: =SUM(B12:E12) | G12: =F12/3 | H12: =IF($F$16=0,0,F12/$F$16)
A13: Miscellaneous | B13: =SUMIFS(Transactions!$C$2:$C$403,Transactions!$D$2:$D$403,$A13,Transactions!$E$2:$E$403,"Mar 2026") | C13: =SUMIFS(Transactions!$C$2:$C$403,Transactions!$D$2:$D$403,$A13,Transactions!$E$2:$E$403,"Apr 2026") | D13: =SUMIFS(Transactions!$C$2:$C$403,Transactions!$D$2:$D$403,$A13,Transactions!$E$2:$E$403,"May 2026") | E13: =SUMIFS(Transactions!$C$2:$C$403,Transactions!$D$2:$D$403,$A13,Transactions!$E$2:$E$403,"Jun 2026") | F13: =SUM(B13:E13) | G13: =F13/3 | H13: =IF($F$16=0,0,F13/$F$16)
A14: Subscriptions | B14: =SUMIFS(Transactions!$C$2:$C$403,Transactions!$D$2:$D$403,$A14,Transactions!$E$2:$E$403,"Mar 2026") | C14: =SUMIFS(Transactions!$C$2:$C$403,Transactions!$D$2:$D$403,$A14,Transactions!$E$2:$E$403,"Apr 2026") | D14: =SUMIFS(Transactions!$C$2:$C$403,Transactions!$D$2:$D$403,$A14,Transactions!$E$2:$E$403,"May 2026") | E14: =SUMIFS(Transactions!$C$2:$C$403,Transactions!$D$2:$D$403,$A14,Transactions!$E$2:$E$403,"Jun 2026") | F14: =SUM(B14:E14) | G14: =F14/3 | H14: =IF($F$16=0,0,F14/$F$16)
A15: Personal Care | B15: =SUMIFS(Transactions!$C$2:$C$403,Transactions!$D$2:$D$403,$A15,Transactions!$E$2:$E$403,"Mar 2026") | C15: =SUMIFS(Transactions!$C$2:$C$403,Transactions!$D$2:$D$403,$A15,Transactions!$E$2:$E$403,"Apr 2026") | D15: =SUMIFS(Transactions!$C$2:$C$403,Transactions!$D$2:$D$403,$A15,Transactions!$E$2:$E$403,"May 2026") | E15: =SUMIFS(Transactions!$C$2:$C$403,Transactions!$D$2:$D$403,$A15,Transactions!$E$2:$E$403,"Jun 2026") | F15: =SUM(B15:E15) | G15: =F15/3 | H15: =IF($F$16=0,0,F15/$F$16)
A16: Total Spending | B16: =SUM(B5:B15) | C16: =SUM(C5:C15) | D16: =SUM(D5:D15) | E16: =SUM(E5:E15) | F16: =SUM(F5:F15) | G16: =SUM(G5:G15) | H16: 1
A17: Total excl. Travel | B17: =B16-B5 | C17: =C16-C5 | D17: =D16-D5 | E17: =E16-E5 | F17: =F16-F5 | G17: =G16-G5 | H17: =IF(F16=0,0,F17/F16)
A19: Card payments made (excluded) | F19: =SUMIFS(Transactions!$C$2:$C$403,Transactions!$D$2:$D$403,"Payments & Adjustments")
